Metadata-Version: 1.0
Name: pyImagingMSpec
Version: 0.1.3
Summary: Python library for processing imaging mass spectrometry data
Home-page: https://github.com/alexandrovteam/pyImagingMSpec
Author: Alexandrov Team, EMBL
Author-email: UNKNOWN
License: UNKNOWN
Platform: UNKNOWN
